molten_jwt/__init__.py
molten_jwt/auth.py
molten_jwt/decorators.py
molten_jwt/exceptions.py
molten_jwt/token.py
molten_jwt/utils.py
molten_jwt-0.3.0.dist-info/LICENSE
molten_jwt-0.3.0.dist-info/METADATA
molten_jwt-0.3.0.dist-info/WHEEL
molten_jwt-0.3.0.dist-info/top_level.txt
molten_jwt-0.3.0.dist-info/RECORD
