Metadata-Version: 2.1
Name: molten-jwt
Version: 0.3.0
Summary: A JSON Web Token library for the Molten web framework
Home-page: https://github.com/androiddrew/molten-jwt
Author: Drew Bednar
Author-email: drew@androiddrew.com
License: MIT
Keywords: molten-jwt molten_jwt molten jwt JWT
Platform: UNKNOWN
Classifier: Development Status :: 2 - Pre-Alpha
Classifier: Environment :: Web Environment
Classifier: Intended Audience :: Developers
Classifier: License :: OSI Approved :: MIT License
Classifier: Natural Language :: English
Classifier: Programming Language :: Python :: 3.6
Classifier: Programming Language :: Python :: 3.7
Requires-Dist: molten (>=0.7.1)
Requires-Dist: Authlib (<0.13,>=0.11)
Provides-Extra: testing
Requires-Dist: pytest ; extra == 'testing'
Requires-Dist: pytest-cov ; extra == 'testing'
Requires-Dist: tox ; extra == 'testing'
